{
  "levels": [
    {
      "id": "P1",
      "name": "Primary 1",
      "skills": [
        {
          "id": "PH-cvc-short-vowels",
          "strand": "phonics",
          "objective": "Decode CVC words with short vowels.",
          "iCanStatement": "I can read short-vowel words.",
          "prereqs": [],
          "itemType": "decode_choice",
          "itemPool": "phonics-L02-cvc-short-vowels",
          "encodePairId": "SP-cvc-short-vowels",
          "mastery": { "window": 12, "accuracyToPass": 0.85, "minItems": 8 }
        },
        {
          "id": "SP-cvc-short-vowels",
          "strand": "spelling",
          "objective": "Spell CVC words with short vowels from tiles.",
          "iCanStatement": "I can spell short-vowel words.",
          "prereqs": ["PH-cvc-short-vowels"],
          "itemType": "build_word",
          "itemPool": "spelling-L02-cvc-short-vowels",
          "encodePairId": "PH-cvc-short-vowels",
          "mastery": { "window": 12, "accuracyToPass": 0.85, "minItems": 8 }
        },
        {
          "id": "PH-digraphs",
          "strand": "phonics",
          "objective": "Decode words with consonant digraphs sh, ch, th, ck.",
          "iCanStatement": "I can read words with sh, ch, th and ck.",
          "prereqs": ["PH-cvc-short-vowels"],
          "itemType": "decode_choice",
          "itemPool": "phonics-L03-digraphs",
          "encodePairId": "SP-digraphs",
          "mastery": { "window": 12, "accuracyToPass": 0.85, "minItems": 8 }
        },
        {
          "id": "SP-digraphs",
          "strand": "spelling",
          "objective": "Spell words with consonant digraphs sh, ch, th, ck from tiles.",
          "iCanStatement": "I can spell words with sh, ch, th and ck.",
          "prereqs": ["PH-digraphs"],
          "itemType": "build_word",
          "itemPool": "spelling-L03-digraphs",
          "encodePairId": "PH-digraphs",
          "mastery": { "window": 12, "accuracyToPass": 0.85, "minItems": 8 }
        },
        {
          "id": "PH-blends",
          "strand": "phonics",
          "objective": "Decode words with initial and final consonant blends.",
          "iCanStatement": "I can read words with consonant blends.",
          "prereqs": ["PH-digraphs"],
          "itemType": "decode_choice",
          "itemPool": "phonics-L04-blends",
          "encodePairId": "SP-blends",
          "mastery": { "window": 12, "accuracyToPass": 0.85, "minItems": 8 }
        },
        {
          "id": "SP-blends",
          "strand": "spelling",
          "objective": "Spell words with initial and final consonant blends from tiles.",
          "iCanStatement": "I can spell words with consonant blends.",
          "prereqs": ["PH-blends"],
          "itemType": "build_word",
          "itemPool": "spelling-L04-blends",
          "encodePairId": "PH-blends",
          "mastery": { "window": 12, "accuracyToPass": 0.85, "minItems": 8 }
        },
        {
          "id": "PH-floss",
          "strand": "phonics",
          "objective": "Decode words ending in doubled ff, ll, ss, zz (FLOSS rule).",
          "iCanStatement": "I can read words that end in ff, ll, ss and zz.",
          "prereqs": ["PH-blends"],
          "itemType": "decode_choice",
          "itemPool": "phonics-L05-floss",
          "encodePairId": "SP-floss",
          "mastery": { "window": 12, "accuracyToPass": 0.85, "minItems": 8 }
        },
        {
          "id": "SP-floss",
          "strand": "spelling",
          "objective": "Spell FLOSS words, doubling final f, l, s, z after a short vowel.",
          "iCanStatement": "I can spell words that end in ff, ll, ss and zz.",
          "prereqs": ["PH-floss"],
          "itemType": "build_word",
          "itemPool": "spelling-L05-floss",
          "encodePairId": "PH-floss",
          "mastery": { "window": 12, "accuracyToPass": 0.85, "minItems": 8 }
        },
        {
          "id": "PH-silent-e",
          "strand": "phonics",
          "objective": "Decode silent-e (magic-e) long-vowel words: a_e, i_e, o_e, u_e.",
          "iCanStatement": "I can read words with a bossy silent e.",
          "prereqs": ["PH-floss"],
          "itemType": "decode_choice",
          "itemPool": "phonics-L06-silent-e",
          "encodePairId": "SP-silent-e",
          "mastery": { "window": 12, "accuracyToPass": 0.85, "minItems": 8 }
        },
        {
          "id": "SP-silent-e",
          "strand": "spelling",
          "objective": "Spell silent-e words, adding the magic e that makes the vowel long.",
          "iCanStatement": "I can spell words with a bossy silent e.",
          "prereqs": ["PH-silent-e"],
          "itemType": "build_word",
          "itemPool": "spelling-L06-silent-e",
          "encodePairId": "PH-silent-e",
          "mastery": { "window": 12, "accuracyToPass": 0.85, "minItems": 8 }
        },
        {
          "id": "PH-vowel-teams",
          "strand": "phonics",
          "objective": "Decode vowel-team long vowels: ai/ay, ee/ea, oa/ow, oo, ew/ue, igh.",
          "iCanStatement": "I can read words where two letters make one long vowel.",
          "prereqs": ["PH-silent-e"],
          "itemType": "decode_choice",
          "itemPool": "phonics-L07-vowel-teams",
          "encodePairId": "SP-vowel-teams",
          "mastery": { "window": 12, "accuracyToPass": 0.85, "minItems": 8 }
        },
        {
          "id": "SP-vowel-teams",
          "strand": "spelling",
          "objective": "Spell vowel-team words, choosing the right team for the long vowel.",
          "iCanStatement": "I can spell words where two letters make one long vowel.",
          "prereqs": ["PH-vowel-teams"],
          "itemType": "build_word",
          "itemPool": "spelling-L07-vowel-teams",
          "encodePairId": "PH-vowel-teams",
          "mastery": { "window": 12, "accuracyToPass": 0.85, "minItems": 8 }
        },
        {
          "id": "PH-r-controlled",
          "strand": "phonics",
          "objective": "Decode r-controlled vowels: ar, or, er, ir, ur (bossy r).",
          "iCanStatement": "I can read words with a bossy r (ar, or, er, ir, ur).",
          "prereqs": ["PH-vowel-teams"],
          "itemType": "decode_choice",
          "itemPool": "phonics-L08-r-controlled",
          "encodePairId": "SP-r-controlled",
          "mastery": { "window": 12, "accuracyToPass": 0.85, "minItems": 8 }
        },
        {
          "id": "SP-r-controlled",
          "strand": "spelling",
          "objective": "Spell r-controlled vowel words (ar, or, er, ir, ur).",
          "iCanStatement": "I can spell words with a bossy r.",
          "prereqs": ["PH-r-controlled"],
          "itemType": "build_word",
          "itemPool": "spelling-L08-r-controlled",
          "encodePairId": "PH-r-controlled",
          "mastery": { "window": 12, "accuracyToPass": 0.85, "minItems": 8 }
        }
      ]
    }
  ]
}
